[
  {
    "__type__": "cc.SpriteFrame",
    "content": {
      "name": "sd_fk013",
      "texture": "1fedbad02",
      "rect": [
        534,
        1465,
        230,
        212
      ],
      "offset": [
        0,
        1
      ],
      "originalSize": [
        230,
        230
      ],
      "rotated": 1,
      "capInsets": [
        0,
        0,
        0,
        0
      ]
    }
  },
  {
    "__type__": "cc.SpriteFrame",
    "content": {
      "name": "sd_fk010",
      "texture": "1fedbad02",
      "rect": [
        877,
        1253,
        224,
        203
      ],
      "offset": [
        -3,
        -3.5
      ],
      "originalSize": [
        230,
        230
      ],
      "capInsets": [
        0,
        0,
        0,
        0
      ]
    }
  },
  {
    "__type__": "cc.SpriteFrame",
    "content": {
      "name": "sd_fk009",
      "texture": "1fedbad02",
      "rect": [
        628,
        685,
        157,
        175
      ],
      "offset": [
        -16.5,
        -14.5
      ],
      "originalSize": [
        230,
        230
      ],
      "rotated": 1,
      "capInsets": [
        0,
        0,
        0,
        0
      ]
    }
  },
  {
    "__type__": "cc.SpriteFrame",
    "content": {
      "name": "sd_fk011",
      "texture": "1fedbad02",
      "rect": [
        628,
        3,
        230,
        212
      ],
      "offset": [
        0,
        1
      ],
      "originalSize": [
        230,
        230
      ],
      "capInsets": [
        0,
        0,
        0,
        0
      ]
    }
  },
  {
    "__type__": "cc.SpriteFrame",
    "content": {
      "name": "sd_fk014",
      "texture": "1fedbad02",
      "rect": [
        628,
        221,
        230,
        212
      ],
      "offset": [
        0,
        1
      ],
      "originalSize": [
        230,
        230
      ],
      "capInsets": [
        0,
        0,
        0,
        0
      ]
    }
  },
  {
    "__type__": "cc.SpriteFrame",
    "content": {
      "name": "sd_fk012",
      "texture": "1fedbad02",
      "rect": [
        628,
        439,
        230,
        212
      ],
      "offset": [
        0,
        1
      ],
      "originalSize": [
        230,
        230
      ],
      "capInsets": [
        0,
        0,
        0,
        0
      ]
    }
  },
  {
    "__type__": "cc.AnimationClip",
    "_name": "闪电 反馈",
    "_duration": 0.21666666666666667,
    "wrapMode": 0,
    "curveData": {
      "comps": {
        "cc.Sprite": {
          "spriteFrame": [
            {
              "frame": 0,
              "value": {
                "__uuid__": "4dYEOq1MhIt4wjffhVc67R"
              }
            },
            {
              "frame": 0.016666666666666666,
              "value": {
                "__uuid__": "37rXUC1UVD3Yc67QXZoOAh"
              }
            },
            {
              "frame": 0.03333333333333333,
              "value": {
                "__uuid__": "4d9+0dlkBBiLiGGpDjet8i"
              }
            },
            {
              "frame": 0.06666666666666667,
              "value": {
                "__uuid__": "5aAcJyjYhOe42wD8bl/gf0"
              }
            },
            {
              "frame": 0.1,
              "value": {
                "__uuid__": "1cEa1BIEdNUIPQ9Axr8y9o"
              }
            },
            {
              "frame": 0.13333333333333333,
              "value": {
                "__uuid__": "55Na3kjCNBRZOz1OkL6z3p"
              }
            },
            {
              "frame": 0.16666666666666666,
              "value": {
                "__uuid__": "aa+2gwBfJCcbKo7S1nkExK"
              }
            },
            {
              "frame": 0.2,
              "value": null
            }
          ]
        }
      },
      "props": {
        "position": []
      },
      "paths": {}
    }
  },
  {
    "__type__": "cc.SpriteFrame",
    "content": {
      "name": "sd_fk015",
      "texture": "1fedbad02",
      "rect": [
        864,
        630,
        230,
        212
      ],
      "offset": [
        0,
        1
      ],
      "originalSize": [
        230,
        230
      ],
      "capInsets": [
        0,
        0,
        0,
        0
      ]
    }
  }
]